dost/__init__.py
dost/__main__.py
dost/chrome.py
dost/clipboard.py
dost/converter.py
dost/excel.py
dost/file.py
dost/folder.py
dost/helpers.py
dost/keyboard.py
dost/mail.py
dost/message.py
dost/mouse.py
dost/new_functions.ipynb
dost/pdf.py
dost/text.py
dost/utility.py
dost/voice.py
dost/windows.py
dost-0.0.4.dist-info/LICENSE
dost-0.0.4.dist-info/WHEEL
dost-0.0.4.dist-info/METADATA
dost-0.0.4.dist-info/RECORD
