Metadata-Version: 2.1
Name: dost
Version: 0.0.4
Summary: DOST is a Python based Utility platform as an Open Source project. We strive to liberate humans from mundane, repetitive tasks, giving them more time to use their intellect and creativity to solve higher-order business challenges and perform knowledge work.
Home-page: https://pybots.ai
License: MIT
Keywords: PyBots,dost,my-dost,utility,Python,Automation,Software BOT,Dost,bots,RPA
Author: PyBOTs
Author-email: support@pybots.ai
Requires-Python: >=3.9.0,<=3.10.40
Classifier: Development Status :: 4 - Beta
Classifier: Environment :: Console
Classifier: Intended Audience :: Developers
Classifier: Intended Audience :: Education
Classifier: Intended Audience :: End Users/Desktop
Classifier: Intended Audience :: Financial and Insurance Industry
Classifier: Intended Audience :: Information Technology
Classifier: Intended Audience :: System Administrators
Classifier: License :: OSI Approved :: MIT License
Classifier: Natural Language :: English
Classifier: Operating System :: Microsoft :: Windows
Classifier: Programming Language :: Python
Classifier: Programming Language :: Python :: 3
Classifier: Programming Language :: Python :: 3.9
Classifier: Programming Language :: Python :: 3.10
Classifier: Topic :: Software Development :: Build Tools
Requires-Dist: Pillow (>=9.2.0,<10.0.0)
Requires-Dist: PyPDF2 (>=2.11.0,<3.0.0)
Requires-Dist: PyQRCode (>=1.2.1,<2.0.0)
Requires-Dist: PyScreeze (>=0.1.28,<0.2.0)
Requires-Dist: WMI (>=1.5.1,<2.0.0)
Requires-Dist: aspose-words (>=22.10.0,<23.0.0)
Requires-Dist: barcode (>=1.0.2,<2.0.0)
Requires-Dist: captcha (>=0.4,<0.5)
Requires-Dist: countryinfo (>=0.1.2,<0.2.0)
Requires-Dist: easyocr (>=1.6.2,<2.0.0)
Requires-Dist: geopy (>=2.2.0,<3.0.0)
Requires-Dist: gspread (>=5.6.2,<6.0.0)
Requires-Dist: gspread-dataframe (>=3.3.0,<4.0.0)
Requires-Dist: imageio (>=2.22.1,<3.0.0)
Requires-Dist: invoice2data (>=0.3.6,<0.4.0)
Requires-Dist: oauth2client (>=4.1.3,<5.0.0)
Requires-Dist: opencv-python (==4.5.5.64)
Requires-Dist: openpyxl (>=3.0.10,<4.0.0)
Requires-Dist: pandas (>=1.5.0,<2.0.0)
Requires-Dist: pdfplumber (>=0.7.5,<0.8.0)
Requires-Dist: phonenumbers (>=8.12.56,<9.0.0)
Requires-Dist: plyer (>=2.0.0,<3.0.0)
Requires-Dist: pygetwindow (>=0.0.9,<0.0.10)
Requires-Dist: pyshorteners (>=1.0.1,<2.0.0)
Requires-Dist: pytesseract (>=0.3.10,<0.4.0)
Requires-Dist: pyttsx3 (>=2.90,<3.0)
Requires-Dist: pytube (>=12.1.0,<13.0.0)
Requires-Dist: pywhatkit (>=5.4,<6.0)
Requires-Dist: pywinauto (>=0.6.8,<0.7.0)
Requires-Dist: pyzbar (>=0.1.9,<0.2.0)
Requires-Dist: requests (>=2.28.1,<3.0.0)
Requires-Dist: speechrecognition (>=3.8.1,<4.0.0)
Requires-Dist: textblob (>=0.17.1,<0.18.0)
Requires-Dist: torch @ https://download.pytorch.org/whl/cpu/torch-1.10.0%2Bcpu-cp39-cp39-linux_x86_64.whl ; sys_platform == "linux"
Requires-Dist: torch @ https://download.pytorch.org/whl/cpu/torch-1.10.0%2Bcpu-cp39-cp39-win_amd64.whl ; sys_platform == "win32" and python_full_version == "3.9.0"
Requires-Dist: torch @ https://download.pytorch.org/whl/cpu/torch-1.12.0%2Bcpu-cp310-cp310-win_amd64.whl ; sys_platform == "win32" and python_full_version == "3.10.0"
Requires-Dist: typeguard (>=2.13.3,<3.0.0)
Requires-Dist: winshell (>=0.6,<0.7)
Requires-Dist: xls2xlsx (>=0.1.5,<0.2.0)
Requires-Dist: xlsx2html (>=0.4.0,<0.5.0)
Requires-Dist: xlwt (>=1.3.0,<2.0.0)
Requires-Dist: yagmail (>=0.15.293,<0.16.0)
Project-URL: Documentation, https://py-bots.github.io/dost/
Project-URL: Repository, https://github.com/py-bots/dost
